ChaonaoLingjixian/README.md
ChaonaoLingjixian/__init__.py
ChaonaoLingjixian/__main__.py
ChaonaoLingjixian/file.epub
ChaonaoLingjixian/index.html
ChaonaoLingjixian/css/__init__.py
ChaonaoLingjixian/css/annotations.css
ChaonaoLingjixian/css/main.css
ChaonaoLingjixian/css/normalize.css
ChaonaoLingjixian/css/popup.css
ChaonaoLingjixian/font/__init__.py
ChaonaoLingjixian/font/fontello.eot
ChaonaoLingjixian/font/fontello.svg
ChaonaoLingjixian/font/fontello.ttf
ChaonaoLingjixian/font/fontello.woff
ChaonaoLingjixian/img/__init__.py
ChaonaoLingjixian/img/annotator-glyph-sprite.png
ChaonaoLingjixian/img/annotator-icon-sprite.png
ChaonaoLingjixian/img/apple-touch-icon.png
ChaonaoLingjixian/img/cancelfullscreen.png
ChaonaoLingjixian/img/close.png
ChaonaoLingjixian/img/fullscreen.png
ChaonaoLingjixian/img/loader.gif
ChaonaoLingjixian/img/menu-icon.png
ChaonaoLingjixian/img/save.png
ChaonaoLingjixian/img/saved.png
ChaonaoLingjixian/img/settings-s.png
ChaonaoLingjixian/img/settings.png
ChaonaoLingjixian/img/star.png
ChaonaoLingjixian/js/__init__.py
ChaonaoLingjixian/js/epub.js
ChaonaoLingjixian/js/epub.min.js
ChaonaoLingjixian/js/epub.min.map
ChaonaoLingjixian/js/hooks.min.js
ChaonaoLingjixian/js/hooks.min.map
ChaonaoLingjixian/js/reader.js
ChaonaoLingjixian/js/reader.js.map
ChaonaoLingjixian/js/reader.min.js
ChaonaoLingjixian/js/reader.min.map
ChaonaoLingjixian/js/hooks/__init__.py
ChaonaoLingjixian/js/hooks/extensions/__init__.py
ChaonaoLingjixian/js/hooks/extensions/highlight.js
ChaonaoLingjixian/js/libs/__init__.py
ChaonaoLingjixian/js/libs/jquery.min.js
ChaonaoLingjixian/js/libs/localforage.min.js
ChaonaoLingjixian/js/libs/screenfull.js
ChaonaoLingjixian/js/libs/screenfull.min.js
ChaonaoLingjixian/js/libs/zip.min.js
ChaonaoLingjixian/js/plugins/__init__.py
ChaonaoLingjixian/js/plugins/hypothesis.js
ChaonaoLingjixian/js/plugins/search.js
chaonao_lingjixian-2022.9.29.0.dist-info/METADATA
chaonao_lingjixian-2022.9.29.0.dist-info/WHEEL
chaonao_lingjixian-2022.9.29.0.dist-info/entry_points.txt
chaonao_lingjixian-2022.9.29.0.dist-info/top_level.txt
chaonao_lingjixian-2022.9.29.0.dist-info/RECORD
